cereggii/atomic_event.c
cereggii/constants.c
cereggii/_cereggii.pyi
cereggii/atomic_int.py
cereggii/cereggii.c
cereggii/thread_handle.py
cereggii/atomic_int.c
cereggii/thread_handle.c
cereggii/constants.py
cereggii/__init__.py
cereggii/atomic_ref.py
cereggii/thread_set.py
cereggii/__about__.py
cereggii/_cereggii.so
cereggii/atomic_event.py
cereggii/count_down_latch.py
cereggii/atomic_ref.c
cereggii/atomic_dict/migrate.c
cereggii/atomic_dict/blocks.c
cereggii/atomic_dict/lookup.c
cereggii/atomic_dict/insert.c
cereggii/atomic_dict/meta.c
cereggii/atomic_dict/__init__.py
cereggii/atomic_dict/node_ops.c
cereggii/atomic_dict/iter.c
cereggii/atomic_dict/atomic_dict.c
cereggii/atomic_dict/delete.c
cereggii/atomic_dict/accessor_storage.c
cereggii-0.6.2.dist-info/RECORD
cereggii-0.6.2.dist-info/LICENSE
cereggii-0.6.2.dist-info/WHEEL
cereggii-0.6.2.dist-info/entry_points.txt
cereggii-0.6.2.dist-info/METADATA
