Metadata-Version: 2.1
Name: cereggii
Version: 0.6.2
Summary: Thread synchronization utilities for Python.
Keywords: multithreading
Author-Email: dpdani <git@danieleparmeggiani.me>
License:                                  Apache License
Classifier: Development Status :: 5 - Production/Stable
Classifier: Intended Audience :: Developers
Classifier: License :: OSI Approved :: Apache Software License
Classifier: Programming Language :: Python
Classifier: Programming Language :: Python :: 3.13
Classifier: Programming Language :: Python :: 3.14
Classifier: Programming Language :: Python :: Implementation :: CPython
Classifier: Programming Language :: Python :: Free Threading :: 4 - Resilient
Classifier: Operating System :: OS Independent
Classifier: Natural Language :: English
Project-URL: Documentation, https://dpdani.github.io/cereggii/
Project-URL: Issues, https://github.com/dpdani/cereggii/issues
Project-URL: Source, https://github.com/dpdani/cereggii
Requires-Python: >=3.13
Provides-Extra: dev
Requires-Dist: build==1.2.2.post1; extra == "dev"
Requires-Dist: pytest==9.0.1; extra == "dev"
Requires-Dist: pytest-reraise==2.1.2; extra == "dev"
Requires-Dist: black==24.10.0; extra == "dev"
Requires-Dist: ruff==0.7.0; extra == "dev"
Provides-Extra: docs
Requires-Dist: mkdocs-material==9.6.11; extra == "docs"
Requires-Dist: mike==2.1.3; extra == "docs"
Requires-Dist: mkdocs-redirects==1.2.2; extra == "docs"
Requires-Dist: mkdocstrings-python==1.16.10; extra == "docs"
Requires-Dist: mkdocs-exclude==1.0.2; extra == "docs"
